{
  "modelVersion" : "2.3",
  "previousArtifactVersion" : "2.2",
  "id" : "NotAuthrozedPage",
  "name" : "NotAuthrozedPage",
  "lastUpdate" : 1666032935115,
  "rows" : [
    [
      {
        "type" : "container",
        "dimension" : {
          "xs" : 12,
          "sm" : 12,
          "md" : 12,
          "lg" : 12
        },
        "propertyValues" : {
          "cssClasses" : {
            "type" : "constant",
            "value" : "row-max-width container"
          },
          "hidden" : {
            "type" : "constant",
            "value" : false
          },
          "repeatedCollection" : {
            "type" : "variable",
            "value" : ""
          }
        },
        "reference" : "83d7d079-08a6-4160-b635-5b76d21ffe5f",
        "hasValidationError" : false,
        "id" : "pbContainer",
        "rows" : [
          [
            {
              "type" : "container",
              "dimension" : {
                "xs" : 12,
                "sm" : 12,
                "md" : 12,
                "lg" : 12
              },
              "propertyValues" : {
                "cssClasses" : {
                  "type" : "constant",
                  "value" : ""
                },
                "hidden" : {
                  "type" : "constant",
                  "value" : false
                },
                "repeatedCollection" : {
                  "type" : "variable",
                  "value" : ""
                }
              },
              "reference" : "a56e0d13-3cf4-47f4-a376-6c7a703fda55",
              "hasValidationError" : false,
              "id" : "pbContainer",
              "rows" : [
                [ ]
              ]
            }
          ],
          [
            {
              "type" : "component",
              "dimension" : {
                "xs" : 12,
                "sm" : 12,
                "md" : 12,
                "lg" : 12
              },
              "propertyValues" : {
                "cssClasses" : {
                  "type" : "constant",
                  "value" : "error-title text-danger"
                },
                "hidden" : {
                  "type" : "constant",
                  "value" : false
                },
                "text" : {
                  "type" : "interpolation",
                  "value" : "Oh no"
                },
                "level" : {
                  "type" : "constant",
                  "value" : "Level 1"
                },
                "alignment" : {
                  "type" : "constant",
                  "value" : "center"
                },
                "allowHTML" : {
                  "type" : "constant",
                  "value" : true
                }
              },
              "reference" : "cf0a4b6f-ed73-4e40-8030-1e5bc69be1f0",
              "hasValidationError" : false,
              "id" : "pbTitle"
            }
          ],
          [
            {
              "type" : "container",
              "dimension" : {
                "xs" : 12,
                "sm" : 12,
                "md" : 12,
                "lg" : 12
              },
              "propertyValues" : {
                "cssClasses" : {
                  "type" : "constant",
                  "value" : ""
                },
                "hidden" : {
                  "type" : "constant",
                  "value" : false
                },
                "repeatedCollection" : {
                  "type" : "variable",
                  "value" : ""
                }
              },
              "reference" : "7657f5b6-230f-481e-bef4-e21bed3c65a2",
              "hasValidationError" : false,
              "id" : "pbContainer",
              "rows" : [
                [ ]
              ]
            }
          ],
          [
            {
              "type" : "component",
              "dimension" : {
                "xs" : 12,
                "sm" : 12,
                "md" : 12,
                "lg" : 12
              },
              "propertyValues" : {
                "cssClasses" : {
                  "type" : "constant",
                  "value" : "error-message text-primary"
                },
                "hidden" : {
                  "type" : "constant",
                  "value" : false
                },
                "text" : {
                  "type" : "interpolation",
                  "value" : "You do not have access to this page or resource."
                },
                "level" : {
                  "type" : "constant",
                  "value" : "Level 3"
                },
                "alignment" : {
                  "type" : "constant",
                  "value" : "center"
                },
                "allowHTML" : {
                  "type" : "constant",
                  "value" : true
                }
              },
              "reference" : "6fe79e82-9cc4-48ce-9598-c22ff7e60ecf",
              "hasValidationError" : false,
              "id" : "pbTitle"
            }
          ],
          [
            {
              "type" : "component",
              "dimension" : {
                "xs" : 12,
                "sm" : 12,
                "md" : 12,
                "lg" : 12
              },
              "propertyValues" : {
                "cssClasses" : {
                  "type" : "constant",
                  "value" : ""
                },
                "hidden" : {
                  "type" : "constant",
                  "value" : false
                },
                "labelHidden" : {
                  "type" : "constant",
                  "value" : true
                },
                "label" : {
                  "type" : "interpolation",
                  "value" : "Default label"
                },
                "labelPosition" : {
                  "type" : "constant",
                  "value" : "top"
                },
                "labelWidth" : {
                  "type" : "constant",
                  "value" : 4
                },
                "allowHTML" : {
                  "type" : "constant",
                  "value" : true
                },
                "text" : {
                  "type" : "interpolation",
                  "value" : "Neque porro quisquam est qui dolorem ipsum quia dolor sit amet,<br/>consectetur,<br/>adipisci velit..."
                },
                "alignment" : {
                  "type" : "constant",
                  "value" : "center"
                }
              },
              "reference" : "882bd879-c462-479d-8eac-8c0b0fb9128f",
              "hasValidationError" : false,
              "id" : "pbText"
            }
          ],
          [
            {
              "type" : "container",
              "dimension" : {
                "xs" : 12,
                "sm" : 12,
                "md" : 12,
                "lg" : 12
              },
              "propertyValues" : {
                "cssClasses" : {
                  "type" : "constant",
                  "value" : ""
                },
                "hidden" : {
                  "type" : "constant",
                  "value" : false
                },
                "repeatedCollection" : {
                  "type" : "variable",
                  "value" : ""
                }
              },
              "reference" : "83876a98-ee8d-484c-b4e3-20d3a4995d5a",
              "hasValidationError" : false,
              "id" : "pbContainer",
              "rows" : [
                [ ]
              ]
            }
          ],
          [
            {
              "type" : "component",
              "dimension" : {
                "xs" : 12,
                "sm" : 12,
                "md" : 12,
                "lg" : 12
              },
              "propertyValues" : {
                "cssClasses" : {
                  "type" : "constant",
                  "value" : "error-message"
                },
                "hidden" : {
                  "type" : "constant",
                  "value" : false
                },
                "text" : {
                  "type" : "interpolation",
                  "value" : "Retour Accueil"
                },
                "type" : {
                  "type" : "constant",
                  "value" : "page"
                },
                "targetUrl" : {
                  "type" : "expression",
                  "value" : "homepageUrl"
                },
                "pageToken" : {
                  "type" : "expression",
                  "value" : "applicationPage.pageToken"
                },
                "processName" : {
                  "type" : "constant"
                },
                "processVersion" : {
                  "type" : "constant"
                },
                "taskId" : {
                  "type" : "constant"
                },
                "caseId" : {
                  "type" : "constant"
                },
                "target" : {
                  "type" : "constant",
                  "value" : "_top"
                },
                "appToken" : {
                  "type" : "expression",
                  "value" : "applicationPage.appToken"
                },
                "urlParams" : {
                  "type" : "constant"
                },
                "alignment" : {
                  "type" : "constant",
                  "value" : "center"
                },
                "buttonStyle" : {
                  "type" : "constant",
                  "value" : "primary"
                },
                "allowHTML" : {
                  "type" : "constant",
                  "value" : true
                }
              },
              "reference" : "5f6766f3-a725-404e-861c-0872eda33707",
              "hasValidationError" : false,
              "id" : "pbLink"
            }
          ],
          [
            {
              "type" : "container",
              "dimension" : {
                "xs" : 12,
                "sm" : 12,
                "md" : 12,
                "lg" : 12
              },
              "propertyValues" : {
                "cssClasses" : {
                  "type" : "constant",
                  "value" : ""
                },
                "hidden" : {
                  "type" : "constant",
                  "value" : false
                },
                "repeatedCollection" : {
                  "type" : "variable",
                  "value" : ""
                }
              },
              "reference" : "17e6eeca-ba61-4d07-b270-3cb4c270d8e0",
              "hasValidationError" : false,
              "id" : "pbContainer",
              "rows" : [
                [
                  {
                    "type" : "component",
                    "dimension" : {
                      "xs" : 12,
                      "sm" : 12,
                      "md" : 12,
                      "lg" : 12
                    },
                    "propertyValues" : {
                      "cssClasses" : {
                        "type" : "constant",
                        "value" : ""
                      },
                      "hidden" : {
                        "type" : "constant",
                        "value" : false
                      },
                      "labelHidden" : {
                        "type" : "constant",
                        "value" : true
                      },
                      "label" : {
                        "type" : "interpolation",
                        "value" : "Default label"
                      },
                      "labelPosition" : {
                        "type" : "constant",
                        "value" : "top"
                      },
                      "labelWidth" : {
                        "type" : "constant",
                        "value" : 4
                      },
                      "allowHTML" : {
                        "type" : "constant",
                        "value" : true
                      },
                      "text" : {
                        "type" : "interpolation",
                        "value" : "<br/>"
                      },
                      "alignment" : {
                        "type" : "constant",
                        "value" : "center"
                      }
                    },
                    "reference" : "eaf731df-6b48-43a2-96de-cb9c1656762d",
                    "hasValidationError" : false,
                    "id" : "pbText"
                  }
                ]
              ]
            }
          ]
        ]
      }
    ]
  ],
  "assets" : [ ],
  "inactiveAssets" : [ ],
  "variables" : {
    "applicationPage" : {
      "type" : "constant",
      "value" : [
        ""
      ],
      "exposed" : true
    }
  },
  "hasValidationError" : false,
  "type" : "fragment"
}