{
  "modelVersion" : "2.3",
  "previousArtifactVersion" : "2.2",
  "id" : "onboardingTableFragment",
  "name" : "onboardingTableFragment",
  "lastUpdate" : 1671045954525,
  "rows" : [
    [
      {
        "type" : "component",
        "dimension" : {
          "xs" : 12,
          "sm" : 1,
          "md" : 1,
          "lg" : 1
        },
        "propertyValues" : {
          "cssClasses" : {
            "type" : "constant",
            "value" : ""
          },
          "hidden" : {
            "type" : "constant",
            "value" : false
          },
          "labelHidden" : {
            "type" : "constant",
            "value" : false
          },
          "label" : {
            "type" : "interpolation",
            "value" : "ID"
          },
          "labelPosition" : {
            "type" : "constant",
            "value" : "top"
          },
          "labelWidth" : {
            "type" : "constant",
            "value" : 4
          },
          "allowHTML" : {
            "type" : "constant",
            "value" : true
          },
          "text" : {
            "type" : "interpolation",
            "value" : "{{employee.id}}"
          },
          "alignment" : {
            "type" : "constant",
            "value" : "left"
          }
        },
        "reference" : "56d82901-4617-488d-aacc-6def037be364",
        "hasValidationError" : false,
        "id" : "pbText"
      },
      {
        "type" : "component",
        "dimension" : {
          "xs" : 12,
          "sm" : 2,
          "md" : 2,
          "lg" : 2
        },
        "propertyValues" : {
          "cssClasses" : {
            "type" : "constant",
            "value" : ""
          },
          "hidden" : {
            "type" : "constant",
            "value" : false
          },
          "labelHidden" : {
            "type" : "constant",
            "value" : false
          },
          "label" : {
            "type" : "interpolation",
            "value" : "Manager"
          },
          "labelPosition" : {
            "type" : "constant",
            "value" : "top"
          },
          "labelWidth" : {
            "type" : "constant",
            "value" : 4
          },
          "allowHTML" : {
            "type" : "constant",
            "value" : true
          },
          "text" : {
            "type" : "interpolation",
            "value" : "{{managerAvatar}} \n {{employee.hiringmanager}}"
          },
          "alignment" : {
            "type" : "constant",
            "value" : "left"
          }
        },
        "reference" : "09d3e25e-d328-4f80-9372-e2660b537309",
        "hasValidationError" : false,
        "id" : "pbText"
      },
      {
        "type" : "component",
        "dimension" : {
          "xs" : 12,
          "sm" : 1,
          "md" : 2,
          "lg" : 2
        },
        "propertyValues" : {
          "cssClasses" : {
            "type" : "constant",
            "value" : ""
          },
          "hidden" : {
            "type" : "constant",
            "value" : false
          },
          "labelHidden" : {
            "type" : "constant",
            "value" : false
          },
          "label" : {
            "type" : "interpolation",
            "value" : "Department"
          },
          "labelPosition" : {
            "type" : "constant",
            "value" : "top"
          },
          "labelWidth" : {
            "type" : "constant",
            "value" : 4
          },
          "allowHTML" : {
            "type" : "constant",
            "value" : true
          },
          "text" : {
            "type" : "interpolation",
            "value" : "{{employee.department}}"
          },
          "alignment" : {
            "type" : "constant",
            "value" : "left"
          }
        },
        "reference" : "38773d69-10de-4ae0-8009-753709dd7981",
        "hasValidationError" : false,
        "id" : "pbText"
      },
      {
        "type" : "component",
        "dimension" : {
          "xs" : 12,
          "sm" : 2,
          "md" : 2,
          "lg" : 2
        },
        "propertyValues" : {
          "cssClasses" : {
            "type" : "constant",
            "value" : ""
          },
          "hidden" : {
            "type" : "constant",
            "value" : false
          },
          "labelHidden" : {
            "type" : "constant",
            "value" : false
          },
          "label" : {
            "type" : "interpolation",
            "value" : "Name"
          },
          "labelPosition" : {
            "type" : "constant",
            "value" : "top"
          },
          "labelWidth" : {
            "type" : "constant",
            "value" : 4
          },
          "allowHTML" : {
            "type" : "constant",
            "value" : true
          },
          "text" : {
            "type" : "interpolation",
            "value" : "{{employee.firstname}}  {{employee.lastname}}"
          },
          "alignment" : {
            "type" : "constant",
            "value" : "left"
          }
        },
        "reference" : "415096cf-b187-480e-a4a5-f2a3ed9f5714",
        "hasValidationError" : false,
        "id" : "pbText"
      },
      {
        "type" : "component",
        "dimension" : {
          "xs" : 12,
          "sm" : 1,
          "md" : 1,
          "lg" : 1
        },
        "propertyValues" : {
          "cssClasses" : {
            "type" : "constant",
            "value" : ""
          },
          "hidden" : {
            "type" : "constant",
            "value" : false
          },
          "labelHidden" : {
            "type" : "constant",
            "value" : false
          },
          "label" : {
            "type" : "interpolation",
            "value" : "Position"
          },
          "labelPosition" : {
            "type" : "constant",
            "value" : "top"
          },
          "labelWidth" : {
            "type" : "constant",
            "value" : 4
          },
          "allowHTML" : {
            "type" : "constant",
            "value" : true
          },
          "text" : {
            "type" : "interpolation",
            "value" : "{{employee.jobposition}}"
          },
          "alignment" : {
            "type" : "constant",
            "value" : "left"
          }
        },
        "reference" : "96b1e251-3ca1-45a6-b044-f50d21dc50b4",
        "hasValidationError" : false,
        "id" : "pbText"
      },
      {
        "type" : "component",
        "dimension" : {
          "xs" : 12,
          "sm" : 1,
          "md" : 1,
          "lg" : 1
        },
        "propertyValues" : {
          "cssClasses" : {
            "type" : "constant",
            "value" : ""
          },
          "hidden" : {
            "type" : "constant",
            "value" : false
          },
          "labelHidden" : {
            "type" : "constant",
            "value" : false
          },
          "label" : {
            "type" : "interpolation",
            "value" : "Office"
          },
          "labelPosition" : {
            "type" : "constant",
            "value" : "top"
          },
          "labelWidth" : {
            "type" : "constant",
            "value" : 4
          },
          "allowHTML" : {
            "type" : "constant",
            "value" : true
          },
          "text" : {
            "type" : "interpolation",
            "value" : "{{employee.homeoffice}}"
          },
          "alignment" : {
            "type" : "constant",
            "value" : "left"
          }
        },
        "reference" : "602c5c8a-afca-422e-b5ac-739a415b0a47",
        "hasValidationError" : false,
        "id" : "pbText"
      },
      {
        "type" : "component",
        "dimension" : {
          "xs" : 12,
          "sm" : 1,
          "md" : 1,
          "lg" : 1
        },
        "propertyValues" : {
          "cssClasses" : {
            "type" : "constant",
            "value" : "vertical-center"
          },
          "hidden" : {
            "type" : "constant",
            "value" : false
          },
          "label" : {
            "type" : "interpolation",
            "value" : "Status"
          },
          "labelPosition" : {
            "type" : "constant",
            "value" : "top"
          },
          "labelWidth" : {
            "type" : "constant",
            "value" : 4
          },
          "alignment" : {
            "type" : "constant",
            "value" : "left"
          },
          "statusString" : {
            "type" : "expression",
            "value" : "employee.status"
          },
          "labelHidden" : {
            "type" : "constant",
            "value" : true
          }
        },
        "reference" : "f99248d3-e241-40c0-a318-d93e139833ea",
        "hasValidationError" : false,
        "id" : "customStatusIndicator"
      },
      {
        "type" : "container",
        "dimension" : {
          "xs" : 12,
          "sm" : 3,
          "md" : 2,
          "lg" : 2
        },
        "propertyValues" : {
          "cssClasses" : {
            "type" : "constant",
            "value" : ""
          },
          "hidden" : {
            "type" : "constant",
            "value" : false
          },
          "repeatedCollection" : {
            "type" : "variable",
            "value" : ""
          }
        },
        "reference" : "774b7637-85b6-4776-a624-b219635ac504",
        "hasValidationError" : false,
        "id" : "pbContainer",
        "rows" : [
          [
            {
              "type" : "container",
              "dimension" : {
                "xs" : 12,
                "sm" : 4,
                "md" : 4,
                "lg" : 4
              },
              "propertyValues" : {
                "cssClasses" : {
                  "type" : "constant",
                  "value" : "vertical-center"
                },
                "hidden" : {
                  "type" : "constant",
                  "value" : false
                },
                "repeatedCollection" : {
                  "type" : "variable",
                  "value" : ""
                }
              },
              "reference" : "dffc6c23-cc1c-4b73-8f67-7f039ab4b280",
              "hasValidationError" : false,
              "id" : "pbContainer",
              "rows" : [
                [
                  {
                    "type" : "component",
                    "dimension" : {
                      "xs" : 12,
                      "sm" : 12,
                      "md" : 12,
                      "lg" : 12
                    },
                    "propertyValues" : {
                      "cssClasses" : {
                        "type" : "constant",
                        "value" : ""
                      },
                      "hidden" : {
                        "type" : "constant",
                        "value" : false
                      },
                      "disabled" : {
                        "type" : "constant",
                        "value" : false
                      },
                      "label" : {
                        "type" : "interpolation",
                        "value" : "<i class=\"glyphicon glyphicon-user\" title=\"Employee Details\"></i>"
                      },
                      "alignment" : {
                        "type" : "constant",
                        "value" : "center"
                      },
                      "buttonStyle" : {
                        "type" : "constant",
                        "value" : "primary"
                      },
                      "action" : {
                        "type" : "constant",
                        "value" : "Open modal"
                      },
                      "assign" : {
                        "type" : "constant",
                        "value" : false
                      },
                      "url" : {
                        "type" : "interpolation"
                      },
                      "responseStatusCode" : {
                        "type" : "variable",
                        "value" : ""
                      },
                      "dataToSend" : {
                        "type" : "constant"
                      },
                      "dataFromSuccess" : {
                        "type" : "variable",
                        "value" : ""
                      },
                      "closeOnSuccess" : {
                        "type" : "constant",
                        "value" : false
                      },
                      "dataFromError" : {
                        "type" : "variable",
                        "value" : ""
                      },
                      "targetUrlOnSuccess" : {
                        "type" : "interpolation"
                      },
                      "collectionToModify" : {
                        "type" : "variable"
                      },
                      "modalId" : {
                        "type" : "expression",
                        "value" : "setSelectedData.initEditGroupModal($item)"
                      },
                      "collectionPosition" : {
                        "type" : "constant",
                        "value" : "Last"
                      },
                      "valueToAdd" : {
                        "type" : "constant"
                      },
                      "removeItem" : {
                        "type" : "variable"
                      },
                      "allowHTML" : {
                        "type" : "constant",
                        "value" : true
                      }
                    },
                    "reference" : "f0fab889-d34b-4c33-934a-e184a141a447",
                    "hasValidationError" : false,
                    "id" : "pbButton"
                  }
                ],
                [
                  {
                    "type" : "container",
                    "dimension" : {
                      "xs" : 12,
                      "sm" : 12,
                      "md" : 12,
                      "lg" : 12
                    },
                    "propertyValues" : {
                      "cssClasses" : {
                        "type" : "constant",
                        "value" : ""
                      },
                      "hidden" : {
                        "type" : "constant",
                        "value" : false
                      },
                      "repeatedCollection" : {
                        "type" : "variable",
                        "value" : ""
                      }
                    },
                    "reference" : "9834a6a5-6c6a-4d0c-881e-f36839b6e9a9",
                    "hasValidationError" : false,
                    "id" : "pbContainer",
                    "rows" : [
                      [ ]
                    ]
                  }
                ]
              ]
            },
            {
              "type" : "container",
              "dimension" : {
                "xs" : 12,
                "sm" : 4,
                "md" : 4,
                "lg" : 4
              },
              "propertyValues" : {
                "cssClasses" : {
                  "type" : "constant",
                  "value" : "vertical-center"
                },
                "hidden" : {
                  "type" : "constant",
                  "value" : false
                },
                "repeatedCollection" : {
                  "type" : "variable",
                  "value" : ""
                }
              },
              "reference" : "27998160-b6a0-4c5f-b4eb-5a606e9cede8",
              "hasValidationError" : false,
              "id" : "pbContainer",
              "rows" : [
                [
                  {
                    "type" : "component",
                    "dimension" : {
                      "xs" : 12,
                      "sm" : 12,
                      "md" : 12,
                      "lg" : 12
                    },
                    "propertyValues" : {
                      "cssClasses" : {
                        "type" : "constant",
                        "value" : ""
                      },
                      "hidden" : {
                        "type" : "constant",
                        "value" : false
                      },
                      "disabled" : {
                        "type" : "constant",
                        "value" : false
                      },
                      "label" : {
                        "type" : "interpolation",
                        "value" : "<i class=\"glyphicon glyphicon-eye-open\" title=\"Case Details\"></i>"
                      },
                      "alignment" : {
                        "type" : "constant",
                        "value" : "center"
                      },
                      "buttonStyle" : {
                        "type" : "constant",
                        "value" : "primary"
                      },
                      "action" : {
                        "type" : "constant",
                        "value" : "Open modal"
                      },
                      "assign" : {
                        "type" : "constant",
                        "value" : false
                      },
                      "url" : {
                        "type" : "interpolation"
                      },
                      "responseStatusCode" : {
                        "type" : "variable",
                        "value" : ""
                      },
                      "dataToSend" : {
                        "type" : "constant"
                      },
                      "dataFromSuccess" : {
                        "type" : "variable",
                        "value" : ""
                      },
                      "closeOnSuccess" : {
                        "type" : "constant",
                        "value" : false
                      },
                      "dataFromError" : {
                        "type" : "variable",
                        "value" : ""
                      },
                      "targetUrlOnSuccess" : {
                        "type" : "interpolation"
                      },
                      "collectionToModify" : {
                        "type" : "variable"
                      },
                      "modalId" : {
                        "type" : "expression",
                        "value" : "setSelectedDataCase.initEditGroupModal($item)"
                      },
                      "collectionPosition" : {
                        "type" : "constant",
                        "value" : "Last"
                      },
                      "valueToAdd" : {
                        "type" : "constant"
                      },
                      "removeItem" : {
                        "type" : "variable"
                      },
                      "allowHTML" : {
                        "type" : "constant",
                        "value" : true
                      }
                    },
                    "reference" : "d671ba7d-63b4-4854-8f18-3b07d0b6c87f",
                    "hasValidationError" : false,
                    "id" : "pbButton"
                  }
                ],
                [
                  {
                    "type" : "container",
                    "dimension" : {
                      "xs" : 12,
                      "sm" : 12,
                      "md" : 12,
                      "lg" : 12
                    },
                    "propertyValues" : {
                      "cssClasses" : {
                        "type" : "constant",
                        "value" : ""
                      },
                      "hidden" : {
                        "type" : "constant",
                        "value" : false
                      },
                      "repeatedCollection" : {
                        "type" : "variable",
                        "value" : ""
                      }
                    },
                    "reference" : "9d02bea4-389c-4855-a019-a6ad51dfa527",
                    "hasValidationError" : false,
                    "id" : "pbContainer",
                    "rows" : [
                      [ ]
                    ]
                  }
                ]
              ]
            },
            {
              "type" : "container",
              "dimension" : {
                "xs" : 12,
                "sm" : 4,
                "md" : 4,
                "lg" : 4
              },
              "propertyValues" : {
                "cssClasses" : {
                  "type" : "constant",
                  "value" : "vertical-center"
                },
                "hidden" : {
                  "type" : "constant",
                  "value" : false
                },
                "repeatedCollection" : {
                  "type" : "variable",
                  "value" : ""
                }
              },
              "reference" : "6ade5e45-c3db-493f-aa8b-4d9205691dff",
              "hasValidationError" : false,
              "id" : "pbContainer",
              "rows" : [
                [
                  {
                    "type" : "component",
                    "dimension" : {
                      "xs" : 12,
                      "sm" : 12,
                      "md" : 12,
                      "lg" : 12
                    },
                    "propertyValues" : {
                      "cssClasses" : {
                        "type" : "constant",
                        "value" : ""
                      },
                      "hidden" : {
                        "type" : "expression",
                        "value" : "!tasks[0].id"
                      },
                      "disabled" : {
                        "type" : "constant",
                        "value" : false
                      },
                      "label" : {
                        "type" : "interpolation",
                        "value" : "<i class=\"glyphicon glyphicon-edit\" title=\"Pending Task\"></i>"
                      },
                      "alignment" : {
                        "type" : "constant",
                        "value" : "center"
                      },
                      "buttonStyle" : {
                        "type" : "constant",
                        "value" : "success"
                      },
                      "action" : {
                        "type" : "constant",
                        "value" : "Open modal"
                      },
                      "assign" : {
                        "type" : "constant",
                        "value" : false
                      },
                      "url" : {
                        "type" : "interpolation"
                      },
                      "responseStatusCode" : {
                        "type" : "variable",
                        "value" : ""
                      },
                      "dataToSend" : {
                        "type" : "constant"
                      },
                      "dataFromSuccess" : {
                        "type" : "variable",
                        "value" : ""
                      },
                      "closeOnSuccess" : {
                        "type" : "constant",
                        "value" : false
                      },
                      "dataFromError" : {
                        "type" : "variable",
                        "value" : ""
                      },
                      "targetUrlOnSuccess" : {
                        "type" : "interpolation"
                      },
                      "collectionToModify" : {
                        "type" : "variable"
                      },
                      "modalId" : {
                        "type" : "expression",
                        "value" : "setSelectedDataTask.initEditGroupModal($item)"
                      },
                      "collectionPosition" : {
                        "type" : "constant",
                        "value" : "Last"
                      },
                      "valueToAdd" : {
                        "type" : "constant"
                      },
                      "removeItem" : {
                        "type" : "variable"
                      },
                      "allowHTML" : {
                        "type" : "constant",
                        "value" : true
                      }
                    },
                    "reference" : "5ebe0d9e-2afd-4c65-a8a4-2bb18363e2c7",
                    "hasValidationError" : false,
                    "id" : "pbButton"
                  }
                ],
                [
                  {
                    "type" : "container",
                    "dimension" : {
                      "xs" : 12,
                      "sm" : 12,
                      "md" : 12,
                      "lg" : 12
                    },
                    "propertyValues" : {
                      "cssClasses" : {
                        "type" : "constant",
                        "value" : ""
                      },
                      "hidden" : {
                        "type" : "constant",
                        "value" : false
                      },
                      "repeatedCollection" : {
                        "type" : "variable",
                        "value" : ""
                      }
                    },
                    "reference" : "a3d824c7-e1cb-4ccd-a690-e55206003de0",
                    "hasValidationError" : false,
                    "id" : "pbContainer",
                    "rows" : [
                      [ ]
                    ]
                  }
                ]
              ]
            }
          ]
        ]
      }
    ]
  ],
  "assets" : [ ],
  "inactiveAssets" : [ ],
  "variables" : {
    "employee" : {
      "type" : "constant",
      "value" : [
        ""
      ],
      "exposed" : true
    },
    "manager" : {
      "type" : "url",
      "value" : [
        "../API/identity/user?p=0&c=10&o=lastname%20ASC&s={{employee.hiringmanager}}"
      ],
      "exposed" : false
    },
    "managerAvatar" : {
      "type" : "expression",
      "value" : [
        " if (!$data.manager[0]) {\r",
        "    return '';\r",
        "}\r",
        "\r",
        "var isCustomIconPath = $data.manager[0].icon && $data.manager[0].icon!='icons/default/icon_user.png';\r",
        "\r",
        "const htmlContentForImage = `<span><img title=\"${$data.employee.manager}\" src=\"${$data.manager[0].icon}\" alt=\"${uiTranslate('User icon')}\" class=\"mini-avatar\"></span>`;\r",
        "\r",
        "const htmlContentForDefaultIcon = `<i title=\"${$data.employee.manager}\" class=\"fa fa-user-circle\"></i>`;\r",
        "\r",
        "return isCustomIconPath ? htmlContentForImage : htmlContentForDefaultIcon;\r",
        "\r"
      ],
      "exposed" : false
    },
    "selectedData" : {
      "type" : "constant",
      "value" : [
        ""
      ],
      "exposed" : true
    },
    "setSelectedData" : {
      "type" : "expression",
      "value" : [
        "return {\r",
        "    initEditGroupModal: function($item) {\r",
        "        $data.selectedData = $item;\r",
        "        \r",
        "        return \"employeeDetailsModal\";\r",
        "    }\r",
        "};"
      ],
      "exposed" : false
    },
    "session" : {
      "type" : "constant",
      "value" : [
        ""
      ],
      "exposed" : true
    },
    "tasks" : {
      "type" : "url",
      "value" : [
        "../API/bpm/humanTask?c=10&p=0&f=state=ready&f=user_id={{session.user_id}}&f=caseId={{employee.id}}"
      ],
      "exposed" : false
    },
    "setSelectedDataTask" : {
      "type" : "expression",
      "value" : [
        "return {\r",
        "    initEditGroupModal: function($item) {\r",
        "        $data.selectedData = $item;\r",
        "        \r",
        "        return \"taskModal\";\r",
        "    }\r",
        "};"
      ],
      "exposed" : false
    },
    "setSelectedDataCase" : {
      "type" : "expression",
      "value" : [
        "return {\r",
        "    initEditGroupModal: function($item) {\r",
        "        $data.selectedData = $item;\r",
        "        \r",
        "        return \"caseDetailsModal\";\r",
        "    }\r",
        "};"
      ],
      "exposed" : false
    }
  },
  "hasValidationError" : false,
  "type" : "fragment"
}